odoo10_addon_partner_noncommercial_multi_relation-10.0.1.0.0.99.dev4-nspkg.pth
odoo/addons/partner_noncommercial_multi_relation/README.rst
odoo/addons/partner_noncommercial_multi_relation/__init__.py
odoo/addons/partner_noncommercial_multi_relation/__manifest__.py
odoo/addons/partner_noncommercial_multi_relation/i18n/nl.po
odoo/addons/partner_noncommercial_multi_relation/i18n/partner_noncommercial_multi_relation.pot
odoo/addons/partner_noncommercial_multi_relation/static/description/icon.png
odoo/addons/partner_noncommercial_multi_relation/views/menu.xml
odoo10_addon_partner_noncommercial_multi_relation-10.0.1.0.0.99.dev4.dist-info/METADATA
odoo10_addon_partner_noncommercial_multi_relation-10.0.1.0.0.99.dev4.dist-info/WHEEL
odoo10_addon_partner_noncommercial_multi_relation-10.0.1.0.0.99.dev4.dist-info/namespace_packages.txt
odoo10_addon_partner_noncommercial_multi_relation-10.0.1.0.0.99.dev4.dist-info/top_level.txt
odoo10_addon_partner_noncommercial_multi_relation-10.0.1.0.0.99.dev4.dist-info/RECORD
